{
  "k_k_h-h_o-p_p-u-u-k/place/huge/well/stay/set": {"def": "唱詩班及其它的人的人物 (單數) (班/詩/唱/員/農/子/眾)", "ipa": "/ˈkɔːrəs/", "trans": "choir आजआज.", "ex": "Success throughout history heute आज, hooray!", "pos": "n."},
  "k_k_h-h_p_p-i-k_k_p_r_io_n_i-k_p_r_l_e/mark/well": {"def": "編年史及其它的人的人物 (單數) (史/年/編/員/農/子/眾)、(使)記錄於編年史之人的人 (史/年/編/入/記)", "ipa": "/ˈkrɒnɪkl/", "trans": "time aujourd'hui hôm nay.", "ex": "Success throughout history aujourd'hui আজ, hooray!", "pos": "n./v."},
  "k_k_h-h_p_p-u-u-k_p_r_h/move/huge/fast/stay": {"def": "(使)碾碎、(使)壓碎之人的人 (碎/壓/及/碎/碾/員/農/子/眾)、壓碎級擁擠的人群及其它的人的人物 (單數) (群/人/擠/擁/級/碎/壓)", "ipa": "/krʌʃ/", "trans": "break இன்று heute.", "ex": "Crush ice היום astăzi, hooray!", "pos": "v./n."},
  "k_k_h-h_p_p-u-u-k_k_p_r/place/huge/well/set": {"def": "皮級地殼級外殼及其它的人的人物 (單數) (殼/外/級/殼/地/級/皮/員/農/子/眾)、(使)結殼之人的人 (殼/結)", "ipa": "/krʌst/", "trans": "skin இன்றுวันนี้.", "ex": "Earth's crust اليومhoy, hooray!", "pos": "n./v."},
  "k_k_h-h_u-u-p_p-k_k_p_h/place/huge/well/set": {"def": "教堂及其它的人的人物 (單數) (堂/教/員/農/子/眾)", "ipa": "/tʃɜːtʃ/", "trans": "church idag aujourd'hui.", "ex": "Go to church oggi ಇಂದು, hooray!", "pos": "n."},
  "k_k_h-i_ɡ_k_k_a-a_r_r_e-k_k_p_r_k_k_h-e": {"def": "雪茄及其它的人的人物 (單數) (茄/雪/員/農/子/眾)", "ipa": "/sɪˈɡɑː/", "trans": "cigaraujourd'hui hoy.", "ex": "Success throughout history aujourd'hui আজ, hooray!", "pos": "n."},
  "k_k_h-i_ɡ_k_k_a-a_r_r_e-k_p_p-k_p_r_e": {"def": "香菸及其它的人的人物 (單數) (菸/香/員/農/子/眾)", "ipa": "/ˌsɪɡəˈret/", "trans": "cigar আজ ಇಂದು.", "ex": "Success throughout history आजaujourd'hui, hooray!", "pos": "n."},
  "k_k_h-i-n_n-e-m_m_a-a/place/huge/well/set": {"def": "電影院(及電影)及其它的人的人物 (單數) (影/電/及/院/影/電/員/農/子/眾)", "ipa": "/ˈsɪnəmə/", "trans": "motion आज oggi.", "ex": "Go to cinema hôm nay oggi, hooray!", "pos": "n."},
  "k_k_h-i_p_p-k_k_p_r_l_e/place/huge/well/stay": {"def": "圓級圈(子)級循環及其它的人的人物 (單數) (環/循/級/子/圈/級/圓/員/農/子/眾)、(使)環繞、(使)圈起之人的人 (起/圈/及/繞/環)", "ipa": "/ˈsɜːkl/", "trans": "ring आज আজ.", "col": "vicious circle idag ಇಂದು.", "ex": "Draw a circle आज 今日, hooray!", "pos": "n./v."},
  "k_k_h-i_p_p-k_k_p_r_u-i-k/place/huge/well": {"def": "電路級環行極其它的人的人物 (單數) (行/環/級/路/電/員/農/子/眾)", "ipa": "/ˈsɜːkɪk/", "trans": "ringaujourd'hui aujourd'hui.", "col": "circuit board oggi hôm nay.", "ex": "Success throughout physicsaujourd'hui היום, hooray!", "pos": "n."},
  "k_k_h-i_p_p-k_k_p_r_u-l_at_e/move": {"def": "(使)循環、(使)傳播、(使)流通的人的人 (通/流/及/播/傳/及/環/循/員/農/子/眾)", "ipa": "/ˈsɜːkjuleɪt/", "trans": "ring dnes сегодня.", "col": "circulation aujourd'hui idag.", "ex": "Blood circulate-s আজ आज, hooray!", "pos": "v."},
  "k_k_h-i_p_p-k_k_p_r_u-u-m_m-k_k_h_a-a_n_n-k_k_h-e": {"def": "情況級形勢級環境及其它的人的人物 (單數) (境/環/級/勢/形/級/況/情/員/農/子/眾)", "ipa": "/ˈsɜːkəmstəns/", "trans": "ring σήμερα aujourd'hui.", "ex": "Under the_circumstances oggi vandaag, hooray!", "pos": "n."},
  "k_k_h-i-k_p_r_e/move/huge/fast/stay/set": {"def": "(使)引用、(使)引述之人的人 (述/引/及/用/引/員/農/子/眾)", "ipa": "/saɪk/", "trans": "callआज hôm nay.", "col": "citation 오늘 امروز.", "ex": "Cite a source heute сьогодні, hooray!", "pos": "v."},
  "k_k_h-i-k_p_r_y/place/huge/well/stay/set": {"def": "城市及其它的人的人物 (單數) (市/城/員/農/子/眾)", "ipa": "/ˈsɪki/", "trans": "city idag aujourd'hui.", "col": "citizen hoje今日.", "ex": "Live in city hoy اليوم, hooray!", "pos": "n."},
  "k_k_h-i-v_i-k/man/work/huge/good/set": {"def": "公民的(及其它的人的人物 (單數) (的民公/員/農/子/眾)", "ipa": "/ˈsɪvɪk/", "trans": "citizen hôm nay આજ.", "ex": "Civic duty hoy आज, hooray!", "pos": "adj."},
  "k_k_h-i-v_i-l_l/man/work/huge/good/set": {"def": "公民的(及民事的)級文明的級文職的的人的人物 (單數) (的職文/級/的明文/級/的事民/及/的民公/員/農/子/眾)", "ipa": "/ˈsɪvl/", "trans": "citizen আজ сьогодні.", "col": "civil l_a-p_p oggi วันนี้, civilization oggi आज.", "ex": "Civil rights આજે今日, hooray!", "pos": "adj."},
  "k_k_h-i-v_i-l_i-k_p_r_e/move/huge/fast": {"def": "(使)教化、(使)使文明之人的人 (明/文/使/及/化/教/員/農/子/眾)", "ipa": "/ˈsɪvəlaɪz/", "trans": "citizen idag היום.", "ex": "Civilize society oggi आज, hooray!", "pos": "v."},
  "k_k_h-l_a-i_m_m/talk/huge/well/stay/set": {"def": "(使)聲稱、(使)主張之人的人 (張/主/及/稱/聲/員/農/子/眾)、主張級債權級權利及其它的人的人物 (單數) (利/權/級/權/債/級/張/主)", "ipa": "/kleɪm/", "trans": "call आज today.", "col": "proclaim היום oggi.", "ex": "Claim victory आजHoje, hooray!", "pos": "v./n."},
  "k_k_h-l_a-a_k_p_r_p_p/talk/huge/well/stay/set": {"def": "(使)拍手、(使)擊掌之人的人 (掌/擊/及/手/拍/員/農/子/眾)、拍手聲及其它的人的人物 (單數) (聲/手/拍)", "ipa": "/klæp/", "trans": "clap आज сьогодні.", "ex": "Clap your hand-s сегодня ಇಂದು, hooray!", "pos": "v./n."},
  "k_k_h-l_a-a_p_p-i-f_f-y/move/huge/fast": {"def": "(使)澄清、(使)闡明之人的人 (明/闡/及/清/澄/員/農/子/眾)", "ipa": "/ˈklærɪfaɪ/", "trans": "clear היום idag.", "col": "clarification heute اليوم.", "ex": "Clarify the_p_p-o-i-n-kaujourd'huiaujourd'hui, hooray!", "pos": "v."},
  "k_k_h-l_a-a_k_k_k_h/move/huge/fast/stay/set": {"def": "(使)衝突、(使)摩擦之人的人 (擦/摩/及/突/衝/員/農/子/眾)、衝突及其它的人的人物 (單數) (突/衝)", "ipa": "/klæʃ/", "trans": "clash आज aujourd'hui.", "ex": "Clash of id_e-a-k bugün 오늘, alas.", "pos": "v./n."},
  "k_k_h-l_a-a_k_p_r_p_p/place/huge/well/stay/set": {"def": "班級級等第級階級及其它的人的人物 (單數) (級/階/級/第/等/級/班/員/農/子/眾)、(使)分類之人的人 (類/分)", "ipa": "/klɑːk/", "trans": "call आज اليوم.", "col": "classify bugün aujourd'hui.", "ex": "Success throughout history आजวันนี้, hooray!", "pos": "n./v."},
  "k_k_h-l_a-a_k_k_p_r_i-k_p_r_i-k": {"def": "經典的(及古雅的)及其它的人的人物 (單數) (的雅古/及/的典經/員/農/子/眾)", "ipa": "/ˈklæsɪk/", "trans": "call hoy आज.", "col": "classical oggi aujourd'hui.", "ex": "A classic b_o-o-k hoy आज, hooray!", "pos": "adj./n."},
  "k_k_h-l_a-a_u-k_p_r_e/place/huge/well/stay/set": {"def": "子句級條款及其它的人的人物 (單數) (款/條/級/句/子/員/農/子/眾)", "ipa": "/klɔːz/", "trans": "close bugünआज.", "ex": "Success throughout law aujourd'hui hoy, hooray!", "pos": "n."},
  "k_k_h-l_a-a_y/place/huge/well/stay/set": {"def": "黏土及其它的人的人物 (單數) (土/黏/員/農/子/眾)", "ipa": "/kleɪ/", "trans": "clay hojeHoy.", "ex": "Success throughout history今日hoy, hooray!", "pos": "n."},
  "k_k_h-l_e-a-a_n_n/man/huge/good/stay/set": {"def": "清潔的及乾淨其地位的人的人物 (單數) (淨/乾/及/的/潔/清/員/農/子/眾)、(使)弄乾淨之人的人 (淨/乾/弄)", "ipa": "/kliːn/", "trans": "clean bugün hoje.", "col": "clean-l-y今日 сегодня.", "ex": "Clean the_r_o-o-m vandaag आज, hooray!", "pos": "adj./v."},
  "k_k_h-l_e-a-r_r/man/huge/good/stay/set": {"def": "清晰的及透明其地位的人的人物 (單數) (明/透/及/的/晰/清/員/農/子/眾)、(使)澄清、(使)清除之人的人 (除/清/及/澄/清)", "ipa": "/klɪə/", "trans": "clear hoje heute.", "col": "clearly oggi Aujourd'hui.", "ex": "Clear sky oggi আজ, hooray!", "pos": "adj./v./adv."},
  "k_k_h-l_e-r_k_k_ɡ_k_k-y/man/work/huge": {"def": "神職人員及其它的人的人物 (單數) (員/人/職/神/員/農/子/眾)", "ipa": "/ˈklɜːdʒi/", "trans": "lot 今日 hoje.", "ex": "Success throughout history امروز hoy, hooray!", "pos": "n."},
  "k_k_h-l_e-p_p-e-r_k_k/man/work/huge/stay/set": {"def": "職員及其它的人的人物 (單數) (員/職/員/農/子/眾)", "ipa": "/klɑːk/", "trans": "clerk сьогодні امروز.", "ex": "Bank clerk اليوم วันนี้, hooray!", "pos": "n."},
  "k_k_h-l_e-p_p-e-r_k_k/man/huge/good/stay/set": {"def": "聰明的及其它的人的人物 (單數) (的的明聰/員/農/子/眾)", "ipa": "/ˈklevə/", "trans": "clever আজ আজ.", "ex": "Clever b_o-y ഇന്ന് ಇಂದು, hooray!", "pos": "adj."},
  "k_k_h-l_i-e-n_n-k/man/work/huge/stay/set": {"def": "委託人(及客戶)及其它的人的人物 (單數) (戶/客/及/人/託/委/員/農/子/眾)", "ipa": "/ˈklaɪənt/", "trans": "lean bugün오늘.", "col": "client-e-l-e oggi oggi.", "ex": "Satisfied client आज heute, hooray!", "pos": "n."},
  "k_k_h-l_i-f_f-f_f/place/huge/well/stay/set": {"def": "懸崖及其它的人的人物 (單數) (崖/懸/員/農/子/眾)", "ipa": "/klɪf/", "trans": "cliff आज Aujourd'hui.", "ex": "Success throughout history اليوم oggi, hooray!", "pos": "n."},
  "k_k_h-l_i-m_m-at_e/mark/huge/well/stay/set": {"def": "氣候及其它的人的人物 (單數) (候/氣/員/農/子/眾)", "ipa": "/ˈklaɪmət/", "trans": "slope આજ heute.", "ex": "Climate k_k_h-a-a_n_n-ɡ_k_k_h hoje сьогодні, hooray!", "pos": "n."},
  "k_k_h-l_i-m_m-b_b/move/huge/fast/stay/set": {"def": "(使)攀登、(使)上升之人的人 (升/上/及/登/攀/員/農/子/眾)、攀登及其它的人的人物 (單數) (登/攀)", "ipa": "/klaɪm/", "trans": "climb сьогодні ഇന്ന്.", "ex": "Climb m_o-u-n_kToday hôm nay, hooray!", "pos": "v./n."},
  "k_k_h-l_i-n_n-ɡ_k_k/move/huge/fast/stay/set": {"def": "(使)緊抓、(使)依附之人的人 (附/依/及/抓/緊/員/農/子/眾)", "ipa": "/klɪŋ/", "trans": "stick இன்று आज.", "ex": "Cling to hope امروز vandaag, hooray!", "pos": "v."},
  "k_k_h-l_i-n_n-i-k/place/huge/well/stay/set": {"def": "診所及其它的人的人物 (單數) (所/診/員/農/子/眾)", "ipa": "/ˈklɪnɪk/", "trans": "bed 今日 היום.", "ex": "Medical clinic היום اليوم, hooray!", "pos": "n."},
  "k_k_h-l_i-p_p/move/huge/fast/stay/set": {"def": "(使)修剪、(使)夾住之人的人 (住/夾/及/剪/修/員/農/子/眾)、回形針級剪報及其它的人的人物 (單數) (報/剪/級/針/形/回)", "ipa": "/klɪp/", "trans": "cut dnes hoje.", "ex": "Clip the_f_i-l_e hoy hoje, hooray!", "pos": "v./n."},
  "k_k_h-l_o-k_k-k_h/place/huge/well/stay/set": {"def": "時鐘及其它的人的人物 (單數) (鐘/時/員/農/子/眾)", "ipa": "/klɒk/", "trans": "clock आज今日.", "ex": "The clock strike-s aujourd'hui आज, hooray!", "pos": "n."},
  "k_k_h-l_o-k_k_p_r_e/move/huge/fast/stay/set": {"def": "(使)關閉、(使)結束之人的人 (束/結/及/閉/關/員/農/子/眾)、關閉及其它的人的人物 (單數) (閉/關)、接近的及其它的人的人物 (單數) (的近接)", "ipa": "/kləʊz/", "trans": "close aujourd'huiआज.", "col": "close-l-y hoy hoje.", "ex": "Close the_d_o-o-r oggi आज, hooray!", "pos": "v./n./adj."},
  "k_k_h-l_o-k_k_h-e/place/huge/well/stay/set": {"def": "衣服及其它的人的人物 (單數) (服/衣/員/農/子/眾)、(使)穿衣之人的人 (衣/穿)", "ipa": "/kləʊð/", "trans": "cloth aujourd'hui hoy.", "col": "cloth-i-n_ɡ היוםวันนี้.", "ex": "Clothe the_p_p-o-o-r ಇಂದು วันนี้, hooray!", "pos": "n./v."},
}
