{
  "equal": {"def": "相等的、平等的、勝任的的人物、等於的人的人人物 (單數) (平/等)", "ipa": "/ˈiːkwəl/", "trans": "same", "col": "equal to, equal rights, without equal (無與倫比), social equal", "ex": "All men are created equal.", "pos": "adj./v./n./adv."},
  "equalitarian/egalitarian": {"def": "平等主義的、平等主義者人物 (單數) (平)", "ipa": "/ɪˌkwɒlɪˈteəriən/", "trans": "equal", "col": "equalitarian society", "ex": "He follow equalitarian principles.", "pos": "adj./n."},
  "equality": {"def": "平等、相等、(數)等式人物 (單數) (平)", "ipa": "/iˈkwɒləti/", "trans": "equal", "col": "racial equality, gender equality, equality of opportunity", "ex": "Fight for gender equality now.", "pos": "n."},
  "equalization/equalisation": {"def": "平等化、平均、(電)均衡人物 (單數) (均)", "ipa": "/ˌiːkwəlaɪˈzeɪʃn/", "trans": "equal", "col": "income equalization", "ex": "Income equalization policy today.", "pos": "n."},
  "equalize/equalise": {"def": "使相等、平均、打成平手、(電)均衡的人的人", "ipa": "/ˈiːkwəlaɪz/", "trans": "same", "col": "equalize scores, equalize opportunity", "ex": "They managed to equalize scores.", "pos": "v./n./adv."},
  "equalizer/equaliser": {"def": "使相等者、(體)平分球、(電)均衡器人物 (單數) (器)", "ipa": "/ˈiːkwəlaɪzə/", "trans": "equal", "col": "graphic equalizer, scored the_equalizer", "ex": "He scored the_late equalizer.", "pos": "n."},
  "equally": {"def": "同樣地、平等地、公平地", "ipa": "/ˈiːkwəli/", "trans": "equal", "col": "equally important", "ex": "Both are equally important now.", "pos": "adv."},
  "equanimity": {"def": "鎮靜、平靜、沉著人物 (單數) (鎮)", "ipa": "/ˌekwəˈnɪməti/", "trans": "stable", "col": "perfect equanimity", "ex": "Accept news with equanimity.", "pos": "n."},
  "equat-": {"def": "赤道、相等的人的人人物 (單數) (赤)", "ipa": "/ɪˈkweɪt-/", "trans": "equal", "col": "equator", "ex": "Cross the_equator tonight.", "pos": "pref./n./adj."},
  "equate": {"def": "等同、使相等、視為平等的人的人", "ipa": "/iˈkweɪt/", "trans": "same", "col": "equate A with B", "ex": "Don't equate wealth with happiness.", "pos": "v./n./adv."},
  "equation": {"def": "等式、方程式、平衡、綜合因素人物 (單數) (式)", "ipa": "/ɪˈkweɪʒn/", "trans": "equal", "col": "solve equation, personal equation, quadratic equation", "ex": "Solve the_quadratic equation now.", "pos": "n."},
  "equator": {"def": "赤道人物 (單數) (赤)", "ipa": "/ɪˈkweɪtə/", "trans": "land", "col": "near the_equator, crossing the_equator", "ex": "Singapore is near the_equator.", "pos": "n."},
  "equatorial": {"def": "赤道的、赤道附近地的人的人物 (單數) (赤)", "ipa": "/ˌekwəˈtɔːriəl/", "trans": "equator", "col": "equatorial forest", "ex": "The_hot equatorial climate.", "pos": "adj./n."},
  "equerry": {"def": "(英王室)侍從官、馬廄員人物 (單數) (官)", "ipa": "/ˈekwəri/", "trans": "man", "col": "royal equerry", "ex": "The_royal equerry arrived now.", "pos": "n."},
  "equi-": {"def": "相等、同等的人的人人物 (單數) (同)", "ipa": "/ˈiːkwɪ-/", "trans": "equal", "col": "equivalent", "ex": "The_equivalent of ten dollars.", "pos": "pref./n./adj."},
  "equi-distant/equidistant": {"def": "等距的、距離相等地的人的人物 (單數) (距)", "ipa": "/ˌiːkwɪˈdɪstənt/", "trans": "equal", "col": "equidistant from", "ex": "A point equidistant from both peaks.", "pos": "adj./n."},
  "equilateral": {"def": "等邊的、等邊形人物 (單數) (邊)", "ipa": "/ˌiːkwɪˈlætərəl/", "trans": "equal", "col": "equilateral triangle", "ex": "Draw an equilateral triangle.", "pos": "adj./n."},
  "equilibria/equilibrium": {"def": "平衡、均衡、平衡狀態人物 (單數) (平)", "ipa": "/ˌiːkwɪˈlɪbriəm/", "trans": "stable", "col": "stable equilibrium, chemical equilibrium, economic equilibrium", "ex": "A state of stable equilibrium.", "pos": "n."},
}
