{
  "distinctive": {"def": "獨特的、有特色的的人的人物 (單數) (特)", "ipa": "/dɪˈstɪŋktɪv/", "trans": "distinct", "col": "distinctive feature, distinctive smell", "ex": "It has a very distinctive smell.", "pos": "adj./n."},
  "distinctively": {"def": "獨特地、有特色地", "ipa": "/dɪˈstɪŋktɪvli/", "trans": "distinctive", "col": "tasted distinctively", "ex": "It tasted so of ginger.", "pos": "adv."},
  "distinctiveness": {"def": "獨特性、特色人物 (單數) (特)", "ipa": "/dɪˈstɪŋktɪvnəs/", "trans": "distinctive", "col": "cultural distinctiveness", "ex": "Its distinctiveness is clear.", "pos": "n."},
  "distinctly": {"def": "清楚地、確實地", "ipa": "/dɪˈstɪŋktli/", "trans": "distinct", "col": "remember distinctly", "ex": "I remember it distinctly now.", "pos": "adv."},
  "distinguish": {"def": "區別、辨別、使傑出、看清的人的人", "ipa": "/dɪˈstɪŋɡwɪʃ/", "trans": "distinction", "col": "distinguish from, distinguish oneself", "ex": "He want to distinguish himself.", "pos": "v./n./adv."},
  "distinguishable": {"def": "可辨別的、可區分的人的人物 (單數) (辨)", "ipa": "/dɪˈstɪŋɡwɪʃəbl/", "trans": "distinguish", "col": "barely distinguishable", "ex": "It was barely distinguishable.", "pos": "adj./n."},
  "distinguishably": {"def": "可辨別地、顯著地", "ipa": "/dɪˈstɪŋɡwɪʃəbli/", "trans": "distinguishable", "col": "differed distinguishably", "ex": "They differed distinguishably.", "pos": "adv."},
  "distinguished": {"def": "卓著的、高貴的、傑出的人的人 (或物) (卓)", "ipa": "/dɪˈstɪŋɡwɪʃt/", "trans": "distinguish", "col": "distinguished service, distinguished guest", "ex": "A distinguished guest arrived.", "pos": "adj./v."},
  "distort": {"def": "扭曲、曲解、失真的的人的人", "ipa": "/dɪˈstɔːt/", "trans": "distortion", "col": "distort facts, distort face", "ex": "Don't distort the_truth tonight.", "pos": "v./n./adv."},
  "distorted": {"def": "扭曲的、失真的人的人 (或物) (歪)", "ipa": "/dɪˈstɔːtɪd/", "trans": "distort", "col": "distorted image", "ex": "The_image was very distorted.", "pos": "adj./v."},
  "distortion": {"def": "扭曲、歪曲、失真人物 (單數) (歪)", "ipa": "/dɪˈstɔːʃn/", "trans": "distort", "col": "gross distortion", "ex": "A gross distortion of history.", "pos": "n."},
  "distort-ional/distortive": {"def": "扭曲的的人的人物 (單數) (歪)", "ipa": "/dɪˈstɔːʃənl/", "trans": "distortion", "col": "distortive effect", "ex": "It had a distortive effect.", "pos": "adj./n."},
  "distract": {"def": "分心、轉移、打擾的人的人", "ipa": "/dɪˈstrækt/", "trans": "distraction", "col": "distract from", "ex": "Don't distract him from work.", "pos": "v./n./adv."},
  "distracted": {"def": "分心的、心煩意亂的人的人 (或物) (亂)", "ipa": "/dɪˈstræktɪd/", "trans": "distract", "col": "distracted air", "ex": "He has a very distracted air.", "pos": "adj./v."},
  "distractedly": {"def": "分心地、心煩意亂地", "ipa": "/dɪˈstræktɪdli/", "trans": "distracted", "col": "looked distractedly", "ex": "She looked distractedly away.", "pos": "adv."},
  "distraction": {"def": "分心、消遣、心煩意亂人物 (單數) (遣)", "ipa": "/dɪˈstrækʃn/", "trans": "distract", "col": "constant distraction, drive to distraction (瘋)", "ex": "Noise drive me to distraction.", "pos": "n."},
  "distractive": {"def": "分心的、消遣地的人的人物 (單數) (遣)", "ipa": "/dɪˈstræktɪv/", "trans": "distraction", "col": "distractive force", "ex": "It was a distractive force.", "pos": "adj./n."},
  "distrain": {"def": "(律)扣押(財產)的人的人", "ipa": "/dɪˈstreɪn/", "trans": "take", "col": "distrain goods", "ex": "They want to distrain his car.", "pos": "v./n./adv."},
  "distraint": {"def": "扣押、扣押物人物 (單數) (扣)", "ipa": "/dɪˈstreɪnt/", "trans": "distrain", "col": "order of distraint", "ex": "The_court gave an order.", "pos": "n."},
  "distraite/distrait": {"def": "心不在焉的人的人物 (單數) (亂)", "ipa": "/dɪˈstreɪt/", "trans": "absent", "col": "seemed distrait", "ex": "She seemed distrait tonight.", "pos": "adj./n."},
  "distraught": {"def": "心煩意亂的、發狂的人的人物 (單數) (瘋)", "ipa": "/dɪˈstrɔːt/", "trans": "upset", "col": "distraught parents", "ex": "They were distraught with fear.", "pos": "adj./n."},
  "distress": {"def": "悲痛、危難、貧困人物、使悲痛的人的人人物 (單數) (痛/危)", "ipa": "/dɪˈstres/", "trans": "distressing", "col": "in distress, distress signal (SOS), respiratory distress", "ex": "The_ship sent a distress signal.", "pos": "n./v./adj."},
  "distressed": {"def": "悲痛的、窮困的人的人 (或物) (痛)", "ipa": "/dɪˈstrest/", "trans": "distress", "col": "distressed area", "ex": "He was very distressed today.", "pos": "adj./v."},
  "distressfully": {"def": "悲切地、痛苦地", "ipa": "/dɪˈstresfəli/", "trans": "distressful", "col": "wept distressfully", "ex": "She wept distressfully tonight.", "pos": "adv."},
  "distressing": {"def": "令人悲痛的、苦惱的人 (或物) (痛)", "ipa": "/dɪˈstresɪŋ/", "trans": "distress", "col": "distressing news", "ex": "The_news was very distressing.", "pos": "adj./n./adv."},
  "distressingly": {"def": "令人悲痛地、極其地", "ipa": "/dɪˈstresɪŋli/", "trans": "distressing", "col": "distressingly thin", "ex": "The_boy was thin so.", "pos": "adv."},
  "distribut-ive/distributary": {"def": "分配的、分流行地的人的人物 (單數) (流)", "ipa": "/dɪˈstrɪbjətɪv/", "trans": "distribute", "col": "river distributary", "ex": "It was a river distributary.", "pos": "adj./n."},
  "distribute": {"def": "分配、分發、散佈、分區的人的人", "ipa": "/dɪˈstrɪbjuːt/", "trans": "distribution", "col": "distribute flyers, distribute wealth", "ex": "They began to distribute food.", "pos": "v./n./adv."},
  "distribution": {"def": "分配、分發、分佈人物 (單數) (佈)", "ipa": "/ˌdɪstrɪˈbjuːʃn/", "trans": "distribute", "col": "equal distribution, population distribution", "ex": "Seek for an equal distribution.", "pos": "n."},
}
