{
  "superficial": {
    "def": "表面的、膚淺的",
    "ipa": "/ˌsuːpəˈfɪʃl/",
    "trans": "superficiality",
    "col": "superficial wound, superficial knowledge",
    "ex": "He has only a superficial knowledge of the subject."
  },
  "superior": {
    "def": "優越的、上級的",
    "ipa": "/suːˈpɪəriə/",
    "trans": "superiority",
    "col": "superior quality, immediate superior",
    "ex": "This model is technically superior to its competitors."
  },
  "supermarket": {
    "def": "超市",
    "ipa": "/ˈsuːpəmɑːkɪt/",
    "trans": "supermarkets",
    "col": "local supermarket",
    "ex": "I buy my groceries at the supermarket."
  },
  "superstition": {
    "def": "迷信",
    "ipa": "/ˌsuːpəˈstɪʃn/",
    "trans": "superstitious",
    "col": "popular superstition",
    "ex": "According to ancient superstition, black cats are unlucky."
  },
  "supervise": {
    "def": "監督、指導",
    "ipa": "/ˈsuːpəvaɪz/",
    "trans": "supervision, supervisor",
    "col": "supervise workers",
    "ex": "I supervise a team of ten people."
  },
  "supplement": {
    "def": "補充、增刊",
    "ipa": "/ˈsʌplɪmənt/",
    "trans": "supplementary",
    "col": "dietary supplement, food supplement",
    "ex": "He takes a vitamin supplement every morning."
  },
  "supply": {
    "def": "供應、補給",
    "ipa": "/səˈplaɪ/",
    "trans": "supplier, supplies",
    "col": "supply and demand, power supply",
    "ex": "The company supplies gas to the whole city."
  },
  "support": {
    "def": "支持、支撐",
    "ipa": "/səˈpɔːt/",
    "trans": "supporter, supportive",
    "col": "financial support, technical support",
    "ex": "He has always supported his family."
  },
  "suppose": {
    "def": "假設、猜想",
    "ipa": "/səˈpəʊz/",
    "trans": "supposed, supposedly",
    "col": "be supposed to",
    "ex": "What do you suppose he meant?"
  },
  "surface": {
    "def": "表面、水面",
    "ipa": "/ˈsɜːfɪs/",
    "trans": "surfacial",
    "col": "on the surface, road surface",
    "ex": "The surface of the table was smooth."
  },
  "surgeon": {
    "def": "外科醫生",
    "ipa": "/ˈsɜːdʒən/",
    "trans": "surgery, surgical",
    "col": "heart surgeon",
    "ex": "The surgeon performed a difficult operation."
  },
  "surgery": {
    "def": "外科手術、診所",
    "ipa": "/ˈsɜːdʒəri/",
    "trans": "surgical, surgeon",
    "col": "undergo surgery, plastic surgery",
    "ex": "He had surgery on his knee."
  },
  "surprise": {
    "def": "驚訝、意外",
    "ipa": "/səˈpraɪz/",
    "trans": "surprised, surprising",
    "col": "take by surprise, in surprise",
    "ex": "I have a surprise for you."
  },
  "surrender": {
    "def": "投降、放棄",
    "ipa": "/səˈrendə/",
    "trans": "surrendered",
    "col": "unconditional surrender",
    "ex": "The rebels were forced to surrender."
  },
  "surround": {
    "def": "圍繞、包圍",
    "ipa": "/səˈraʊnd/",
    "trans": "surrounding, surroundings",
    "col": "be surrounded by",
    "ex": "The house is surrounded by trees."
  },
  "survey": {
    "def": "調查、測量",
    "ipa": "/ˈsɜːveɪ/",
    "trans": "surveyor",
    "col": "conduct a survey, a recent survey",
    "ex": "A recent survey showed that people are working longer hours."
  },
  "survival": {
    "def": "生存、倖存",
    "ipa": "/səˈvaɪvl/",
    "trans": "survive, survivor",
    "col": "survival of the fittest",
    "ex": "His chances of survival are quite good."
  },
  "survive": {
    "def": "倖存、活下來",
    "ipa": "/səˈvaɪv/",
    "trans": "survivor, survival",
    "col": "survive a crash",
    "ex": "Of the six people in the plane, only two survived."
  },
  "suspect": {
    "def": "懷疑、嫌疑犯",
    "ipa": "/səˈspekt/",
    "trans": "suspicion, suspicious",
    "col": "suspect fraud",
    "ex": "I suspect that he is lying."
  },
  "suspicion": {
    "def": "懷疑、疑心",
    "ipa": "/səˈspɪʃn/",
    "trans": "suspect, suspicious",
    "col": "under suspicion, above suspicion",
    "ex": "I have a strong suspicion that she is involved."
  },
  "sustain": {
    "def": "維持、支撐",
    "ipa": "/səˈsteɪn/",
    "trans": "sustainable, sustenance",
    "col": "sustain growth",
    "ex": "He was unable to sustain his interest."
  },
  "swallow": {
    "def": "吞下、燕子",
    "ipa": "/ˈswɒləʊ/",
    "trans": "swallowed",
    "col": "swallow hard",
    "ex": "The pills are difficult to swallow."
  },
  "sway": {
    "def": "搖動、支配",
    "ipa": "/sweɪ/",
    "trans": "swaying",
    "col": "hold sway",
    "ex": "The trees were swaying in the wind."
  },
  "swear": {
    "def": "發誓、咒罵",
    "ipa": "/sweə/",
    "trans": "swearing, swore, sworn",
    "col": "swear by, swear at",
    "ex": "I swear I'm telling the truth."
  }
}