{
  "destitute": {"def": "赤貧的、缺乏的、窮人的人的人物 (單數) (窮)", "ipa": "/ˈdestɪtjuːt/", "trans": "poor", "col": "destitute of, help the_destitute", "ex": "They were left destitute by war.", "pos": "adj./n."},
  "destitution": {"def": "赤貧、缺乏人物 (單數) (窮)", "ipa": "/ˌdestɪˈtjuːʃn/", "trans": "destitute", "col": "total destitution", "ex": "He died in total destitution.", "pos": "n."},
  "destroy": {"def": "打碎、摧毀、破壞、殺死、使失敗的人的人", "ipa": "/dɪˈstrɔɪ/", "trans": "destruction", "col": "destroy building, destroy life", "ex": "The_fire manage to destroy all.", "pos": "v./n./adv."},
  "destroyer": {"def": "破壞者、驅逐艦人物 (單數) (壞/艦)", "ipa": "/dɪˈstrɔɪə/", "trans": "destroy", "col": "missile destroyer", "ex": "The_destroyer sailed at dawn.", "pos": "n."},
  "destruct": {"def": "(飛彈等)自毀、破壞的人的人人物 (單數) (毀)", "ipa": "/dɪˈstrʌkt/", "trans": "destruction", "col": "self-destruct", "ex": "The_rocket will self-destruct.", "pos": "v./n./adj."},
  "destructible": {"def": "可破壞的、易損的人的人物 (單數) (毀)", "ipa": "/dɪˈstrʌktəbl/", "trans": "destruct", "col": "highly destructible", "ex": "The_device is highly destructible.", "pos": "adj./n."},
  "destruction": {"def": "破壞、毀滅、原因人物 (單數) (毀)", "ipa": "/dɪˈstrʌkʃn/", "trans": "destructive", "col": "mass destruction, leading to destruction", "ex": "War lead to mass destruction.", "pos": "n."},
  "destructive": {"def": "破壞性的、有害地 (毀)", "ipa": "/dɪˈstrʌktɪv/", "trans": "destruction", "col": "destructive habits", "ex": "He has many destructive habits.", "pos": "adj./adv."},
  "destructively": {"def": "破壞性地、有害地", "ipa": "/dɪˈstrʌktɪvli/", "trans": "destructive", "col": "behaved destructively", "ex": "He behaved very destructively.", "pos": "adv."},
  "destructiveness": {"def": "破壞性人物 (單數) (毀)", "ipa": "/dɪˈstrʌktɪvnəs/", "trans": "destructive", "col": "great destructiveness", "ex": "A sense of great destructiveness.", "pos": "n."},
  "destructor": {"def": "破壞者、垃圾焚化爐人物 (單數) (壞)", "ipa": "/dɪˈstrʌktə/", "trans": "destruct", "col": "waste destructor", "ex": "Use the_waste destructor now.", "pos": "n."},
  "desuetude": {"def": "廢止、不用人物 (單數) (廢)", "ipa": "/dɪˈswiːtjuːd/", "trans": "disuse", "col": "fall into desuetude", "ex": "The_law fall into desuetude.", "pos": "n."},
  "desulphurize/desulphurise": {"def": "脫硫的人的人", "ipa": "/ˌdiːˈsʌlfəraɪz/", "trans": "sulphur", "col": "desulphurize fuel", "ex": "They need to desulphurize oil.", "pos": "v./n./adv."},
  "desultory": {"def": "散漫的、斷斷續續地 (散)", "ipa": "/ˈdesəltəri/", "trans": "random", "col": "desultory talk", "ex": "We had a desultory talk today.", "pos": "adj./adv."},
  "desultorily": {"def": "散漫地、斷斷續續地", "ipa": "/ˈdesəltərili/", "trans": "desultory", "col": "worked desultorily", "ex": "He worked desultorily all day.", "pos": "adv."},
  "detach": {"def": "分離、拆卸、派遣的人的人", "ipa": "/dɪˈtætʃ/", "trans": "detached", "col": "detach from, detach oneself", "ex": "I began to detach from them all.", "pos": "v./n./adv."},
  "detachable": {"def": "可拆卸的人的人物 (單數) (拆)", "ipa": "/dɪˈtætʃəbl/", "trans": "detach", "col": "detachable hood", "ex": "The_coat has a detachable hood.", "pos": "adj./n."},
  "detached": {"def": "超然的、分離的人的人 (或物) (超)", "ipa": "/dɪˈtætʃt/", "trans": "detach", "col": "detached house (獨立屋), detached air", "ex": "He has a very detached air now.", "pos": "adj./v."},
  "detachment": {"def": "超然、分離、派遣隊人物 (單數) (超/隊)", "ipa": "/dɪˈtætʃmənt/", "trans": "detach", "col": "military detachment", "ex": "A small detachment was sent.", "pos": "n."},
  "detail": {"def": "細節、詳情、派遣的人的人人物 (單數) (細)", "ipa": "/ˈdiːteɪl/", "trans": "detailed", "col": "in detail, go into detail", "ex": "Please give me a full detail log.", "pos": "n./v./adj./adv."},
  "detailed": {"def": "詳細的、精確的人的人 (或物) (細)", "ipa": "/ˈdiːteɪld/", "trans": "detail", "col": "detailed report", "ex": "He gave us a detailed report today.", "pos": "adj./v."},
}
