{
  "short": {
    "def": "短的、矮的、缺乏的",
    "ipa": "/ʃɔːt/",
    "trans": "shorten, shortly, shortness",
    "col": "short story, in short",
    "ex": "It's a very short walk to the station."
  },
  "shortage": {
    "def": "不足、缺乏、缺少",
    "ipa": "/ˈʃɔːtɪdʒ/",
    "trans": "short (形容詞)",
    "col": "food shortage, water shortage",
    "ex": "There is a severe shortage of housing."
  },
  "shortcoming": {
    "def": "缺點、短處",
    "ipa": "/ˈʃɔːtkʌmɪŋ/",
    "trans": "shortcomings",
    "col": "common shortcomings",
    "ex": "Despite his shortcomings, he is a good man."
  },
  "shortcut": {
    "def": "捷徑、撇步",
    "ipa": "/ˈʃɔːtkʌt/",
    "trans": "shortcuts",
    "col": "take a shortcut",
    "ex": "He took a shortcut through the park."
  },
  "shorten": {
    "def": "縮短、變短、減少",
    "ipa": "/ˈʃɔːtn/",
    "trans": "short (形容詞)",
    "col": "shorten the distance",
    "ex": "We need to shorten the meeting."
  },
  "shortly": {
    "def": "不久、立刻、簡短地",
    "ipa": "/ˈʃɔːtli/",
    "trans": "short (形容詞)",
    "col": "shortly after, shortly before",
    "ex": "I'll be with you shortly."
  },
  "shorts": {
    "def": "短褲",
    "ipa": "/ʃɔːts/",
    "trans": "short (形容詞)",
    "col": "pair of shorts",
    "ex": "He was wearing a T-shirt and shorts."
  },
  "shot": {
    "def": "發射、射擊、照片",
    "ipa": "/ʃɒt/",
    "trans": "shoot (動詞)",
    "col": "give it a shot, mug shot",
    "ex": "That was a good shot."
  },
  "shotgun": {
    "def": "獵槍、散彈槍",
    "ipa": "/ˈʃɒtɡʌn/",
    "trans": "shotguns",
    "col": "double barreled shotgun",
    "ex": "He carried a shotgun for hunting."
  },
  "should": {
    "def": "應該、將要、竟然",
    "ipa": "/ʃʊd/",
    "trans": "shall (過去式)",
    "col": "should have",
    "ex": "You should see a doctor."
  },
  "shoulder": {
    "def": "肩膀、山肩、肩負",
    "ipa": "/ˈeəldə/",
    "trans": "shoulders",
    "col": "broad shoulders, shoulder to shoulder",
    "ex": "He put his hand on my shoulder."
  },
  "shout": {
    "def": "大喊、大叫、喊叫聲",
    "ipa": "/ʃaʊt/",
    "trans": "shouted",
    "col": "shout for help, shout at",
    "ex": "Don't shout at me!"
  },
  "shove": {
    "def": "推、擠、強使",
    "ipa": "/ʃʌv/",
    "trans": "shoved",
    "col": "shove aside",
    "ex": "The crowd began to shove."
  },
  "shovel": {
    "def": "鏟子、鐵鍬、挖",
    "ipa": "/ˈʃʌvl/",
    "trans": "shovels",
    "col": "steam shovel",
    "ex": "He used a shovel to clear the snow."
  },
  "show": {
    "def": "顯示、展示、表現",
    "ipa": "/ʃəʊ/",
    "trans": "showed, shown, showy",
    "col": "show off, on show",
    "ex": "Let me show you the way."
  },
  "shower": {
    "def": "陣雨、淋浴、洗",
    "ipa": "/ˈʃaʊə/",
    "trans": "showering, showery",
    "col": "take a shower, baby shower",
    "ex": "I'm going to take a shower."
  },
  "showy": {
    "def": "艷麗的、炫耀的",
    "ipa": "/ˈʃəʊi/",
    "trans": "showily",
    "col": "showy flowers",
    "ex": "She wore a showy dress to the party."
  },
  "shrewd": {
    "def": "精明的、狡猾的",
    "ipa": "/ʃruːd/",
    "trans": "shrewdly",
    "col": "shrewd businessman",
    "ex": "He made a shrewd investment."
  },
  "shriek": {
    "def": "尖叫、大笑、尖叫聲",
    "ipa": "/ʃriːk/",
    "trans": "shrieked",
    "col": "shriek with laughter",
    "ex": "She gave a loud shriek of terror."
  },
  "shrill": {
    "def": "尖銳的、刺耳的、尖叫",
    "ipa": "/ʃrɪl/",
    "trans": "shrilly",
    "col": "shrill voice",
    "ex": "The whistle made a shrill sound."
  }
}