{
  "burn": {"def": "燃燒、燒傷、發熱、灼熱、燒傷的人物、燃燒地 (燒)", "ipa": "/bɜːn/", "trans": "burning, burnt/burned", "col": "burn down, burn out, burn the midnight oil (熬夜), severe burn", "ex": "The fire started to burn more brightly.", "pos": "v./n./adv."},
  "burned/burnt": {"def": "燒焦的、燒傷的、燒毀的人 (或物)", "ipa": "/bɜːnd/", "trans": "burn (名詞/動詞/副詞)", "col": "burnt toast, sunburned", "ex": "He applied ointment to his sunburnt skin.", "pos": "v./adj./n."},
  "burner": {"def": "爐嘴、燃燒器、燒東西的人 (單數)", "ipa": "/ˈbɜːnə/", "trans": "burn (名詞/動詞/副詞)", "col": "gas burner, bunsen burner", "ex": "Don't touch the stove; the burner is still hot.", "pos": "n."},
  "burning": {"def": "燃燒的、灼熱的、迫切的、燃燒的人 (或物) (燒)", "ipa": "/ˈbɜːnɪŋ/", "trans": "burn (名詞/動詞/副詞)", "col": "burning issue, burning desire", "ex": "Unemployment is a burning issue in the region.", "pos": "adj./n./adv."},
  "burnish": {"def": "擦亮、磨光、磨光的人 (或物)、磨光地 (亮)", "ipa": "/ˈbɜːnɪʃ/", "trans": "polished", "col": "burnish metal", "ex": "The metal was burnished until it shone like a mirror.", "pos": "v./n./adv."},
  "burnt": {"def": "燒焦的、燒黑的 (單數)", "ipa": "/bɜːnt/", "trans": "burn", "col": "burnt orange", "ex": "The walls were painted a rich burnt orange color.", "pos": "adj./v."},
  "burp": {"def": "打嗝、使打嗝、打嗝的人 (或物)、打嗝地 (嗝)", "ipa": "/bɜːp/", "trans": "belch", "col": "intentional burp", "ex": "The baby gave a giant burp after finishing his bottle.", "pos": "v./n./adv."},
  "burr/bur": {"def": "(植物)刺果、(鑽)毛刺、去除毛刺的人、刺果地 (刺)", "ipa": "/bɜː/", "trans": "roughness", "col": "remove the burr", "ex": "The machine helps to remove the burr from metal edges.", "pos": "n./v./adv."},
  "burrito": {"def": "墨西哥捲餅 (單數)", "ipa": "/bəˈriːtəʊ/", "trans": "burritos (複數)", "col": "beef burrito", "ex": "He ordered a spicy beef burrito for lunch.", "pos": "n."},
  "burrow": {"def": "洞穴、地道、鑽洞、翻找、地道的人物、在地道地 (洞)", "ipa": "/ˈbʌrəʊ/", "trans": "dig", "col": "rabbit burrow, burrow into", "ex": "The mole started to burrow into the garden soil.", "pos": "n./v./adv."},
  "bursa": {"def": "(醫)黏液囊 (單數)", "ipa": "/ˈbɜːsə/", "trans": "bursae (複數)", "col": "swollen bursa", "ex": "He has a swollen bursa in his shoulder joint.", "pos": "n."},
  "bursar": {"def": "會計主任、(學)司庫 (單數)", "ipa": "/ˈbɜːsə/", "trans": "treasurer", "col": "university bursar", "ex": "The university bursar is responsible for financial matters.", "pos": "n."},
  "bursary": {"def": "獎學金、助學金、司庫辦公室 (單數)", "ipa": "/ˈbɜːsəri/", "trans": "bursaries (複數)", "col": "educational bursary", "ex": "She was awarded an educational bursary to study abroad.", "pos": "n."},
  "burst": {"def": "爆裂、爆發、炸開、突發、爆裂的人 (或物)、爆裂地 (爆)", "ipa": "/bɜːst/", "trans": "bursting", "col": "burst into tears, burst out laughing, star burst, cloud burst (大暴雨)", "ex": "The balloon burst with a loud bang.", "pos": "v./n./adv."},
  "bursting": {"def": "爆滿的、充滿的的人 (或物) (滿)", "ipa": "/ˈbɜːstɪŋ/", "trans": "burst (名詞/動詞/副詞)", "col": "bursting with pride", "ex": "The stadium was bursting with excited football fans.", "pos": "adj./adv."},
  "bury": {"def": "埋葬、掩埋、隱藏、埋葬的人 (或物)、埋葬地 (葬)", "ipa": "/ˈberi/", "trans": "burial, buried", "col": "bury the hatchet (和解), bury one's head in the sand (逃避現實)", "ex": "They decided to bury the ancient jar in the garden.", "pos": "v./n./adv."},
  "bus": {"def": "公車、巴士、乘公車、公車的人物、公車地 (公車)", "ipa": "/bʌs/", "trans": "buses/busses", "col": "bus stop, bus lane, bus terminal, miss the bus", "ex": "I take the bus to work every morning.", "pos": "n./v./adv."},
  "busboy": {"def": "(美餐)碗盤清理工 (單數)", "ipa": "/ˈbʌsbɔɪ/", "trans": "worker", "col": "busy busboy", "ex": "The busy busboy quickly cleared the dirty table.", "pos": "n."},
  "busby": {"def": "(英)熊皮高帽 (單數)", "ipa": "/ˈbʌzbi/", "trans": "hat", "col": "guardsman's busby", "ex": "The guardsman wore a tall busby for the parade.", "pos": "n."},
  "bush": {"def": "灌木、矮樹叢、(俚)荒野、長滿灌木的人物、灌木地 (灌木)", "ipa": "/bʊʃ/", "trans": "bushy, bushes", "col": "beat around the bush (轉彎抹角), bushfire, blackberry bush", "ex": "A rabbit ran into the thick green bush.", "pos": "n./adj./v./adv."},
  "bushel": {"def": "蒲式耳(容量)、大量的人 (或物) (蒲)", "ipa": "/ˈbʊʃl/", "trans": "measure", "col": "bushel of apples", "ex": "They harvested over a bushel of fresh apples.", "pos": "n./adv."},
  "bushido": {"def": "武士道 (單數)", "ipa": "/ˈbuːʃiːdəʊ/", "trans": "code", "col": "spirit of bushido", "ex": "The samurais lived according to the code of bushido.", "pos": "n."},
  "bushman": {"def": "叢林居民、布希曼人", "ipa": "/ˈbʊʃmən/", "trans": "bushmen (複數)", "col": "kalahari bushman", "ex": "The Kalahari bushmen are famous for their tracking skills.", "pos": "n."},
  "bushy": {"def": "灌木茂密的、(毛髮)濃密的的人 (或物)", "ipa": "/ˈbʊʃi/", "trans": "bush (名詞/形容詞/副詞)", "col": "bushy eyebrows, bushy tail", "ex": "The squirrel has a long, bushy tail.", "pos": "adj./n."},
  "busily": {"def": "忙碌地、熱鬧地", "ipa": "/ˈbɪzɪli/", "trans": "busy (形容詞/動詞/副詞)", "col": "working busily", "ex": "Everyone was working busily to meet the deadline.", "pos": "adv."},
  "business": {"def": "商業、生意、事情、職責、商業的人物、商業地 (商)", "ipa": "/ˈbɪznəs/", "trans": "businesses", "col": "on business, do business with, none of your business (不關你的事), business hours", "ex": "He is in town on business for a few days.", "pos": "n./v./adj./adv."},
  "businesslike": {"def": "公事公辦的、有效率的", "ipa": "/ˈbɪznəslaɪk/", "trans": "professional", "col": "businesslike manner", "ex": "She handled the complex matter in a very businesslike manner.", "pos": "adj."},
  "businessman": {"def": "商人、企業家", "ipa": "/ˈbɪznəsmən/", "trans": "businessmen (複數)", "col": "successful businessman", "ex": "The successful businessman owns several local companies.", "pos": "n."},
  "businesswoman": {"def": "女商人、女企業家", "ipa": "/ˈbɪznəswʊmən/", "trans": "businesswomen (複數)", "col": "ambitious businesswoman", "ex": "She is an ambitious businesswoman who runs a tech firm.", "pos": "n."},
  "busk": {"def": "街頭談唱、街頭表演的人物、街頭地 (演)", "ipa": "/bʌsk/", "trans": "busker, busking", "col": "busk for money", "ex": "He used to busk in the subway to earn some extra cash.", "pos": "v./n./adv."},
  "busker": {"def": "街頭藝人", "ipa": "/ˈbʌskə/", "trans": "busk (動詞/名詞/副詞)", "col": "talented busker", "ex": "The talented busker played his guitar for the commuters.", "pos": "n."},
  "busking": {"def": "街頭表演、街頭藝人的活動的人 (或物) (演)", "ipa": "/ˈbʌskɪŋ/", "trans": "busker", "col": "go busking", "ex": "Busking is allowed in certain areas of the city center.", "pos": "n./adv."},
  "buss": {"def": "(舊)親吻、親吻的人 (或物)、親吻地 (吻)", "ipa": "/bʌs/", "trans": "kiss", "col": "loud buss", "ex": "He gave his grandmother a loud buss on the cheek.", "pos": "n./v./adv."},
  "bust": {"def": "胸像、(俚)破產、搜捕、打破、半身、失敗的人、破產地 (破)", "ipa": "/bʌst/", "trans": "busted", "col": "bust-up (劇烈爭吵), drug bust, go bust, bust a gut (竭盡全力)", "ex": "The company went bust after only six months of trading.", "pos": "n./v./adj./adv."},
  "busted": {"def": "(俚)當場被抓、破產的、壞掉的人的人 (或物)", "ipa": "/ˈbʌstɪd/", "trans": "bust (名詞/動詞/副詞)", "col": "get busted", "ex": "The teenagers got busted for smoking in the toilets.", "pos": "v./adj./n."}
}
