{
  "hypothetically/mind-ly": {"def": "假設地、(喻)假想地的人的人物 (單數) (假)", "ipa": "/ˌhaɪpəˈθetɪkli/", "trans": "hypothetical", "col": "speak-ing hypothetically", "ex": "Hypothetically, what would you do?", "pos": "adv."},
  "hypoxi-": {"def": "氧、低的人的人人物 (單數) (氧/低)", "ipa": "/haɪˈpɒks-/", "trans": "weak", "col": "hypoxia", "ex": "Patient suffer-ing from acute hypoxia.", "pos": "pref./n./adj."},
  "hypoxia/body/weak": {"def": "(醫)缺氧(症)人物 (單數) (缺)", "ipa": "/haɪˈpɒksiə/", "trans": "hypoxi-", "col": "tissue hypoxia", "ex": "Hypoxia can cause brain damage, alas.", "pos": "n."},
  "hyps-": {"def": "高、測的人的人人物 (單數) (高)", "ipa": "/ˈhaɪps-/", "trans": "huge", "col": "hypsometer", "ex": "Using a hypsometer to measure altitude.", "pos": "pref./n./adj."},
  "hypsometer/huge/machine": {"def": "(物)測高計、(喻)測影儀人物 (單數) (計)", "ipa": "/hɪpˈsɒmɪtə/", "trans": "hyps-", "col": "precision hypsometer", "ex": "The_hypsometer show-s we are high up.", "pos": "n."},
  "hyrax/animal": {"def": "(動)蹄兔及其它的人的人物 (單數) (兔)", "ipa": "/ˈhaɪræks/", "trans": "animal", "col": "rock hyrax", "ex": "A hyrax sun-ning itself on the_rock.", "pos": "n."},
  "hys_s_op/plant/food": {"def": "(植)牛膝草、(藥)牛膝草油人物 (單數) (草)", "ipa": "/ˈhɪsəp/", "trans": "food", "col": "fragrant hys_s_op", "ex": "Purify with a branch of hys_s_op, sir.", "pos": "n."},
  "hysterectomy/body/bad": {"def": "(醫)子宮切除術人物 (單數) (切)", "ipa": "/ˌhɪstəˈrektəmi/", "trans": "bad", "col": "undergo hysterectomy", "ex": "She had a total hysterectomy today.", "pos": "n."},
  "hysteri-": {"def": "狂、騷的人的人人物 (單數) (狂)", "ipa": "/hɪˈstɪəri-/", "trans": "bad", "col": "hysteria", "ex": "The_news caused mass hysteria, alas.", "pos": "pref./n./adj."},
  "hysteria/bad/mind": {"def": "(醫)歇斯底里、(喻)情緒失控、癔病人物 (單數) (瘋/狂)", "ipa": "/hɪˈstɪəriə/", "trans": "hysteri-", "col": "mass hysteria, religious hysteria", "ex": "There was hysteria in the_street, alas.", "pos": "n."},
  "hysteric/bad-": {"def": "歇斯底里的、(喻)異常激動地的人的人物、(醫)歇斯底里患者人物 (單數) (瘋)", "ipa": "/hɪˈsterɪk/", "trans": "hysteria", "col": "hysteric outburst", "ex": "She gave an hysteric laugh, indeed.", "pos": "adj./n."},
  "hysterical/bad-": {"def": "歇斯底里的、(喻)情緒失控的、(口)極其可笑地的人的人物 (單數) (瘋/笑)", "ipa": "/hɪˈsterɪkl/", "trans": "hysteric", "col": "hysterical laughter, hysterical fans", "ex": "The_crowd became quite hysterical tonight.", "pos": "adj./n."},
  "hysterically/bad-ly": {"def": "歇斯底里地、失控地、極其可笑地", "ipa": "/hɪˈsterɪkli/", "trans": "hysterical", "col": "weeping hysterically", "ex": "She was cry-ing hysterically, alas.", "pos": "adv."},
  "hz/unit/sound": {"def": "(物)赫茲(頻率單位)人物 (單數) (赫)", "ipa": "/hɜːts/", "trans": "huge", "col": "high frequency hz", "ex": "The_machine operate-s at 50 hz.", "pos": "n."},
  "i": {"def": "我(主格)的人人物 (單數) (我)", "ipa": "/aɪ/", "trans": "man", "col": "i am, i can, i think", "ex": "I am a student of history, sir.", "pos": "pron./n."},
  "i-": {"def": "同、類的人的人人物 (單數) (同/類)", "ipa": "/aɪ-/", "trans": "same", "col": "identical", "ex": "An identical twin brother, indeed.", "pos": "pref./n./adj."},
  "iamb/talk/poem": {"def": "(詩)短長格、(喻)抑揚格人物 (單數) (格)", "ipa": "/ˈaɪæmb/", "trans": "good", "col": "iambic pentameter", "ex": "Shakespeare wrote in iambic rhythm.", "pos": "n."},
  "iambic/talk-": {"def": "抑揚格的、短長格地的人的人物 (單數) (格)", "ipa": "/aɪˈæmbɪk/", "trans": "iamb", "col": "iambic verse", "ex": "An iambic line of poetry tonight.", "pos": "adj./n."},
  "ibex/animal": {"def": "(動)北山羊及其它的人的人物 (單數) (羊)", "ipa": "/ˈaɪbeks/", "trans": "animal", "col": "alpine ibex", "ex": "An ibex climbing the_steep cliff.", "pos": "n."},
  "ibis/bird": {"def": "(動)朱鷺、(喻)長嘴鳥及其它的人的人物 (單數) (鷺)", "ipa": "/ˈaɪbɪs/", "trans": "bird", "col": "sacred ibis", "ex": "A sacred ibis by the_river nile.", "pos": "n."},
  "ice/cold": {"def": "冰、(喻)冷淡的人物、(體)冰場人物、(俚)鑽石人物、(俚)毒品(冰毒)人物、結冰、(喻)冷藏的人的人 (冰/鑽/毒/冷)", "ipa": "/aɪs/", "trans": "stay", "col": "ice cream, ice age, ice hockey, on ice, break the_ice", "ex": "The_lake is covered in thin ice.", "pos": "n./v./adj."},
  "ice-": {"def": "冰的人的人人物 (單數) (冰)", "ipa": "/aɪs-/", "trans": "stay", "col": "iceberg", "ex": "The_ship hit a large iceberg, alas.", "pos": "pref./n./adj."},
  "iceberg/cold/huge": {"def": "冰山、(喻)冷淡的人及其它的人的人物 (單數) (山)", "ipa": "/ˈaɪsbɜːɡ/", "trans": "ice", "col": "tip of iceberg", "ex": "Only the_tip of the_iceberg, sir.", "pos": "n."},
  "iceboat/car": {"def": "冰上帆船及其它的人的人物 (單數) (船)", "ipa": "/ˈaɪsbəʊt/", "trans": "ice", "col": "fast iceboat", "ex": "Sailing an iceboat on the_bay.", "pos": "n."},
  "ice-bound/cold": {"def": "被冰封閉的、(喻)冰天雪地地的人的人物 (單數) (封)", "ipa": "/ˈaɪsbaʊnd/", "trans": "ice", "col": "ice-bound harbor", "ex": "The_ship was ice-bound for months.", "pos": "adj./n."},
  "ice-box/house": {"def": "(美)冰盒、(喻)冰箱、(俚)牢房人物 (單數) (盒/箱/牢)", "ipa": "/ˈaɪsbɒks/", "trans": "ice", "col": "cold ice-box", "ex": "Put the_milk in the_ice-box, sir.", "pos": "n."},
  "icecap/cold": {"def": "冰帽、(專)極地冰原人物 (單數) (帽)", "ipa": "/ˈaɪskæp/", "trans": "ice", "col": "polar icecap", "ex": "The_polar icecap is melting fast.", "pos": "n."},
  "ice-c_old/cold-": {"def": "冰冷的、(喻)冷酷地的人的人物 (單數) (冷)", "ipa": "/ˌaɪs ˈkəʊld/", "trans": "ice", "col": "ice-c_old water", "ex": "An ice-c_old beer in summer tonight.", "pos": "adj./n."},
  "ice-cream/food": {"def": "冰淇淋及其它的人的人人物 (單數) (淋)", "ipa": "/ˌaɪs ˈkriːm/", "trans": "ice", "col": "ice-cream cone", "ex": "I like strawberry ice-cream, sir.", "pos": "n./adj."},
  "iced/cold-": {"def": "加冰的、(喻)冷藏地的人的人物 (單數) (冰)", "ipa": "/aɪst/", "trans": "ice", "col": "iced tea, iced coffee", "ex": "A glass of iced tea, please.", "pos": "adj./v."},
  "icefall/cold/huge": {"def": "冰瀑及其它的人的人物 (單數) (瀑)", "ipa": "/ˈaɪsfɔːl/", "trans": "ice", "col": "giant icefall", "ex": "Climbing up the_frozen icefall.", "pos": "n."},
  "iceman/man/cold": {"def": "賣冰者、(喻)冰上運動員、(史)冰河期人人物 (單數) (員)", "ipa": "/ˈaɪsmən/", "trans": "ice", "col": "cold iceman", "ex": "The_iceman deliver-s ice today.", "pos": "n."},
  "ice-p_i_c_k/tool/cold": {"def": "破冰錐及其它的人的人物 (單數) (錐)", "ipa": "/ˈaɪspɪk/", "trans": "ice", "col": "sharp ice-p_i_c_k", "ex": "Using an ice-p_i_c_k to break ice.", "pos": "n."},
  "icy/cold-": {"def": "冰冷的、(喻)冷淡地的人的人物 (單數) (冷)", "ipa": "/ˈaɪsi/", "trans": "ice", "col": "icy wind, icy stare", "ex": "The_stair-s are very icy tonight.", "pos": "adj./n."},
  "icily/cold-ly": {"def": "冰冷地、冷淡地", "ipa": "/ˈaɪsəli/", "trans": "icy", "col": "smile-d icily", "ex": "She spoke icily to the_man, alas.", "pos": "adv."},
  "ici-nes_s/coldness": {"def": "冰冷、冷淡人物 (單數) (冷)", "ipa": "/ˈaɪsinəs/", "trans": "icy", "col": "ici-nes_s of winter", "ex": "Feel the_ici-nes_s of the_water.", "pos": "n."},
  "icon/mark/god": {"def": "偶像、(宗)聖像人物、(計)圖標人物、(喻)象徵人物 (單數) (像/標/徵)", "ipa": "/ˈaɪkɒn/", "trans": "see", "col": "cultural icon, desktop icon", "ex": "Click the_icon to start the_app.", "pos": "n."},
  "iconic/mark-": {"def": "偶像的、(喻)象徵性的、著名的地的人的人物 (單數) (著)", "ipa": "/aɪˈkɒnɪk/", "trans": "icon", "col": "iconic building, iconic image", "ex": "The_Eiffel Tower is iconic, sir.", "pos": "adj./n."},
  "iconoclas_m/bad/god": {"def": "聖像破除、(喻)破除迷信人物 (單數) (破)", "ipa": "/aɪˈkɒnəklæzm/", "trans": "bad", "col": "cultural iconoclas_m", "ex": "His work show-s strong iconoclas_m.", "pos": "n."},
  "iconoclas_t/man/bad": {"def": "破除偶像者、(喻)特立獨行者人物 (單數) (員)", "ipa": "/aɪˈkɒnəklæst/", "trans": "iconoclas_m", "col": "political iconoclas_t", "ex": "He was a famous social iconoclas_t.", "pos": "n."},
  "ict-": {"def": "打、襲的人的人人物 (單數) (打/襲)", "ipa": "/ˈɪkt-/", "trans": "bad", "col": "ictus", "ex": "A sudden ictus of the_heart, alas.", "pos": "pref./n./adj."},
  "icter-": {"def": "黃、疸的人的人人物 (單數) (黃/疸)", "ipa": "/ˈɪktə-/", "trans": "bad", "col": "icterus", "ex": "A case of neonatal icterus found.", "pos": "pref./n./adj."},
  "icterus/sickness/body": {"def": "(醫)黃疸及其它的人的人物 (單數) (疸)", "ipa": "/ˈɪktərəs/", "trans": "icter-", "col": "severe icterus", "ex": "Icterus results in yellow skin, sir.", "pos": "n."},
  "icy-": {"def": "冰的人的人人物 (單數) (冰)", "ipa": "/aɪsi-/", "trans": "ice", "col": "icicle", "ex": "A long icicle hang-ing from roof.", "pos": "pref./n./adj."},
  "icicle/cold": {"def": "垂冰、冰柱、(喻)冷淡的人人物 (單數) (柱)", "ipa": "/ˈaɪsɪkl/", "trans": "icy-", "col": "frozen icicle", "ex": "Look at the_sharp icicle-s, sir.", "pos": "n."},
  "id/mind": {"def": "(心/分)本我、(計)標識符人物 (單數) (我/標)", "ipa": "/ɪd/", "trans": "man", "col": "ego and id", "ex": "The_conflict between ego and id.", "pos": "n."},
  "idempotent/math": {"def": "(數/計)冪等的及其它的人的人物 (單數) (冪)", "ipa": "/ˌaɪdemˈpəʊtnt/", "trans": "same", "col": "idempotent operation", "ex": "The_function is idempotent, sir.", "pos": "adj./n."},
}
