{
  "dextrose": {"def": "(化)右旋糖、葡萄糖人物 (單數) (糖)", "ipa": "/ˈdekstrəʊz/", "trans": "sugar", "col": "pure dextrose", "ex": "Dextrose is a form of sugar.", "pos": "n."},
  "dharm-": {"def": "法的人的人人物 (單數) (法)", "ipa": "/ˈdɑːm-/", "trans": "law", "col": "dharma (法)", "ex": "He follows the_dharma path.", "pos": "pref./n./adj."},
  "dharma/Dharma": {"def": "達摩、法、正法、義務人物 (單數) (法)", "ipa": "/ˈdɑːmə/", "trans": "duty", "col": "eternal dharma", "ex": "Dharma is a core Hindu concept.", "pos": "n."},
  "dhoti": {"def": "(印)腰布、托蒂人物 (單數) (布)", "ipa": "/ˈdəʊti/", "trans": "cloth", "col": "cotton dhoti", "ex": "He wore a white cotton dhoti.", "pos": "n."},
  "dhow": {"def": "(阿)單桅帆船人物 (單數) (船)", "ipa": "/daʊ/", "trans": "boat", "col": "wooden dhow", "ex": "The_wooden dhow sailed south.", "pos": "n."},
  "di-": {"def": "二、兩倍的人的人人物 (單數) (二)", "ipa": "/daɪ-/", "trans": "two", "col": "dioxide (二氧化物)", "ex": "Carbon dioxide is a gas.", "pos": "pref./n./adj."},
  "dia-": {"def": "穿過、橫過、完全的人的人人物 (單數) (過)", "ipa": "/ˈdaɪə-/", "trans": "through", "col": "diameter (直徑)", "ex": "The_diameter is ten cm long.", "pos": "pref./n./adj."},
  "diabetes": {"def": "(醫)糖尿病人物 (單數) (糖)", "ipa": "/ˌdaɪəˈbiːtiːz/", "trans": "disease", "col": "suffer from diabetes", "ex": "He must manage his diabetes.", "pos": "n."},
  "diabetic": {"def": "糖尿病的、糖尿病患者的人的人物 (單數) (糖)", "ipa": "/ˌdaɪəˈbetɪk/", "trans": "diabetes", "col": "diabetic diet", "ex": "She has to follow a diabetic diet.", "pos": "adj./n."},
  "diablerie": {"def": "魔鬼行為、法術、邪惡人物 (單數) (邪)", "ipa": "/diˈɑːbləri/", "trans": "devilry", "col": "black diablerie", "ex": "A sense of black diablerie here.", "pos": "n."},
  "diabolic/diabolical": {"def": "魔鬼的、惡魔般地 (魔)", "ipa": "/ˌdaɪəˈbɒlɪk/", "trans": "devil", "col": "diabolical plan", "ex": "He has a very diabolical plan.", "pos": "adj./adv."},
  "diabolically": {"def": "魔鬼般地、極其地", "ipa": "/ˌdaɪəˈbɒlɪkli/", "trans": "diabolo", "col": "diabolically clever", "ex": "The_scheme was clever.", "pos": "adv."},
  "diabolism": {"def": "魔鬼崇拜、邪惡人物 (單數) (邪)", "ipa": "/daɪˈæbəlɪzəm/", "trans": "devil", "col": "ancient diabolism", "ex": "The_book studies diabolism.", "pos": "n."},
  "diacaustic": {"def": "(光)透射焦散的人的人物 (單數) (光)", "ipa": "/ˌdaɪəˈkɔːstɪk/", "trans": "light", "col": "diacaustic curve", "ex": "It was a diacaustic curve.", "pos": "adj./n."},
  "diachronic": {"def": "(語)歷時的人的人物 (單數) (時)", "ipa": "/ˌdaɪəˈkrɒnɪk/", "trans": "history", "col": "diachronic study", "ex": "He did a diachronic study.", "pos": "adj./n."},
  "diacritic": {"def": "區別性的、變音符號的人的人物 (單數) (變)", "ipa": "/ˌdaɪəˈkrɪtɪk/", "trans": "mark", "col": "diacritic mark", "ex": "Add a diacritic mark here.", "pos": "adj./n."},
  "diadem": {"def": "王冠、冠冕、裝飾的人的人人物 (單數) (冠)", "ipa": "/ˈdaɪədem/", "trans": "crown", "col": "royal diadem", "ex": "The_king wore a royal diadem.", "pos": "n./v./adj."},
  "diaeresis/dieresis": {"def": "(語)分音符人物 (單數) (分)", "ipa": "/daɪˈerəsɪs/", "trans": "mark", "col": "double diaeresis", "ex": "The_word has a diaeresis.", "pos": "n."},
  "diag-": {"def": "對角的人的人人物 (單數) (角)", "ipa": "/ˈdaɪəɡ-/", "trans": "angle", "col": "diagonal", "ex": "The_line is diagonal here.", "pos": "pref./n./adj."},
  "diagnose": {"def": "診斷、判斷的人的人", "ipa": "/ˈdaɪəɡnəʊz/", "trans": "diagnosis", "col": "diagnose as, diagnose ill", "ex": "The_doctor failed to diagnose it.", "pos": "v./n./adv."},
  "diagnosis": {"def": "診斷、診斷書、判斷人物 (單數) (診)", "ipa": "/ˌdaɪəɡˈnəʊsɪs/", "trans": "diagnose", "col": "clinical diagnosis, final diagnosis", "ex": "A final diagnosis was made.", "pos": "n."},
  "diagnostic": {"def": "診斷的、判別的人的人物 (單數) (診)", "ipa": "/ˌdaɪəɡˈnɒstɪk/", "trans": "diagnosis", "col": "diagnostic tool, diagnostic test", "ex": "We used a new diagnostic tool.", "pos": "adj./n."},
  "diagnostician": {"def": "診斷專家人物 (單數) (專)", "ipa": "/ˌdaɪəɡnɒˈstɪʃn/", "trans": "diagnose", "col": "skilled diagnostician", "ex": "He is a skilled diagnostician.", "pos": "n."},
  "diagnostics": {"def": "診斷學、診斷程序人物 (單數) (診)", "ipa": "/ˌdaɪəɡˈnɒstɪks/", "trans": "diagnosis", "col": "run diagnostics", "ex": "The_system is running diagnostics.", "pos": "n."},
  "diagonal": {"def": "對角線的、斜的的人的人物 (單數) (對)", "ipa": "/daɪˈæɡənl/", "trans": "angle", "col": "diagonal line, diagonal move", "ex": "He made a quick diagonal move.", "pos": "adj./n./adv."},
  "diagonally": {"def": "對角線地、斜對地", "ipa": "/daɪˈæɡənəli/", "trans": "diagonal", "col": "cut diagonally", "ex": "Cut the_bread diagonally.", "pos": "adv."},
  "diagram": {"def": "圖表、圖解、示意圖的人物、示意的的人的人人物 (單數) (圖)", "ipa": "/ˈdaɪəɡræm/", "trans": "map", "col": "Venn diagram, block diagram", "ex": "He drew a simple block diagram.", "pos": "n./v./adj."},
  "diagrammatic/diagrammatical": {"def": "圖表的、圖解的人的人物 (單數) (圖)", "ipa": "/ˌdaɪəɡrəˈmætɪk/", "trans": "diagram", "col": "diagrammatic view", "ex": "It was in a diagrammatic form.", "pos": "adj./n."},
  "dial": {"def": "刻度盤、撥號盤的人的人人物 (單數) (撥)", "ipa": "/ˈdaɪəl/", "trans": "call", "col": "dial code, dial up, speed dial", "ex": "Please dial the_correct code.", "pos": "v./n./adj./adv."},
  "dialect": {"def": "方言、土語、地方話人物 (單數) (方)", "ipa": "/ˈdaɪəlekt/", "trans": "language", "col": "local dialect, dialect speaker", "ex": "He spoke in a local dialect.", "pos": "n."},
  "dialectal": {"def": "方言的、地方話的人的人物 (單數) (語)", "ipa": "/ˌdaɪəˈlektl/", "trans": "dialect", "col": "dialectal variation", "ex": "There is a dialectal difference.", "pos": "adj./n."},
  "dialectical/dialectic": {"def": "辯證的、辯證法的人的人物 (單數) (辯)", "ipa": "/ˌdaɪəˈlektɪkl/", "trans": "dialectics", "col": "dialectical logic", "ex": "He studied dialectical logic.", "pos": "adj./n."},
  "dialectician": {"def": "辯證學者人物 (單數) (辯)", "ipa": "/ˌdaɪəlekˈtɪʃn/", "trans": "dialectic", "col": "famous dialectician", "ex": "He was a famous dialectician.", "pos": "n."},
  "dialectics": {"def": "辯證法人物 (單數) (辯)", "ipa": "/ˌdaɪəˈlektɪks/", "trans": "dialectic", "col": "Hegelian dialectics", "ex": "He followed Hegelian dialectics.", "pos": "n."},
  "dialogue/dialog": {"def": "對話、會談的人的人人物 (單數) (話)", "ipa": "/ˈdaɪəlɒɡ/", "trans": "talk", "col": "constructive dialogue, internal dialogue", "ex": "We need constructive dialogue.", "pos": "v./n./adj./adv."},
  "dialysis": {"def": "(醫)透析、洗腎人物 (單數) (洗)", "ipa": "/daɪˈæləsɪs/", "trans": "clean", "col": "kidney dialysis", "ex": "He is on kidney dialysis now.", "pos": "n."},
  "diamant-": {"def": "金剛石的人的人人物 (單數) (鑽)", "ipa": "/ˈdaɪəmənt-/", "trans": "diamond", "col": "diamantine", "ex": "It had a diamantine glow.", "pos": "pref./n./adj."},
  "diamantine/diamantiferous": {"def": "金剛石的人的人物 (單數) (鑽)", "ipa": "/ˌdaɪəˈmæntiːn/", "trans": "diamond", "col": "diamantine luster", "ex": "The_rock has a diamantine look.", "pos": "adj./n."},
  "diameter": {"def": "直徑、橫徑人物 (單數) (直)", "ipa": "/daɪˈæmɪtə/", "trans": "width", "col": "internal diameter", "ex": "The_internal diameter is small.", "pos": "n."},
  "diametric/diametrical": {"def": "直徑的、正好相反的人的人物 (單數) (直)", "ipa": "/ˌdaɪəˈmetrɪk/", "trans": "opposite", "col": "diametrical opposite", "ex": "They have diametrical views.", "pos": "adj./n."},
  "diametrically": {"def": "完全地、直徑地", "ipa": "/ˌdaɪəˈmetrɪkli/", "trans": "diametric", "col": "diametrically opposed", "ex": "Our views are diametrically so.", "pos": "adv."},
  "diamond": {"def": "鑽石、菱形、棒球場、金剛石的人的人物 (單數) (鑽)", "ipa": "/ˈdaɪəmənd/", "trans": "gem", "col": "diamond ring, diamond jubilee, baseball diamond", "ex": "He bought a diamond ring.", "pos": "n./adj."},
  "diapason": {"def": "(樂)音域、貫穿、主音栓人物 (單數) (音)", "ipa": "/ˌdaɪəˈpeɪzn/", "trans": "range", "col": "full diapason", "ex": "The_organ has a full diapason.", "pos": "n."},
  "diaper/diper": {"def": "尿布、菱形花紋人物、換尿布的人的人人物 (單數) (尿)", "ipa": "/ˈdaɪəpə/", "trans": "cloth", "col": "change a diaper", "ex": "It's time to change the_diaper.", "pos": "n./v./adj."},
  "diaphanous": {"def": "透明的、精緻地 (透)", "ipa": "/daɪˈæfənəs/", "trans": "clear", "col": "diaphanous dress", "ex": "She wore a diaphanous gown.", "pos": "adj./adv."},
  "diaphoretic": {"def": "發汗的、發汗劑的人的人物 (單數) (汗)", "ipa": "/ˌdaɪəfəˈretɪk/", "trans": "sweat", "col": "diaphoretic drug", "ex": "He used a diaphoretic drug.", "pos": "adj./n."},
  "diaphragm": {"def": "橫膈膜、震動板、避孕隔膜人物 (單數) (膈)", "ipa": "/ˈdaɪəfræm/", "trans": "membrane", "col": "contraceptive diaphragm", "ex": "The_diaphragm helps in breath.", "pos": "n."},
  "diarchy": {"def": "雙頭政治、兩頭統治人物 (單數) (雙)", "ipa": "/ˈdaɪɑːki/", "trans": "rule", "col": "ancient diarchy", "ex": "It was an ancient diarchy.", "pos": "n."},
  "diarist": {"def": "記日記的人人物 (單數) (日)", "ipa": "/ˈdaɪərɪst/", "trans": "diary", "col": "famous diarist", "ex": "Pepys was a famous diarist.", "pos": "n."},
  "diarrhoea/diarrhea": {"def": "腹瀉人物 (單數) (瀉)", "ipa": "/ˌdaɪəˈrɪə/", "trans": "illness", "col": "suffer from diarrhoea", "ex": "He has a bad case of diarrhoea.", "pos": "n."},
  "diary": {"def": "日記、日誌人物 (單數) (日)", "ipa": "/ˈdaɪəri/", "trans": "diarist", "col": "keep a diary, dear diary", "ex": "She began to keep a full diary.", "pos": "n."},
  "diastole": {"def": "舒張、心臟擴張的人物 (單數) (舒)", "ipa": "/daɪˈæstəli/", "trans": "heart", "col": "cardiac diastole", "ex": "Diastole is the_rest period.", "pos": "n."},
  "diastolic": {"def": "舒張的、心臟舒張的人的人物 (單數) (舒)", "ipa": "/ˌdaɪəˈstɒlɪk/", "trans": "diastole", "col": "diastolic pressure (舒張壓)", "ex": "Check your diastolic pressure.", "pos": "adj./n."},
  "diathermy": {"def": "(醫)透熱療法人物 (單數) (熱)", "ipa": "/ˈdaɪəθɜːmi/", "trans": "heat", "col": "surgical diathermy", "ex": "He received diathermy today.", "pos": "n."},
  "diathesis": {"def": "(醫)素質、特異體質人物 (單數) (質)", "ipa": "/daɪˈæθəsɪs/", "trans": "body", "col": "hemorrhagic diathesis", "ex": "He has a bleeding diathesis.", "pos": "n."},
  "diatom": {"def": "(植)矽藻人物 (單數) (藻)", "ipa": "/ˈdaɪətəm/", "trans": "algae", "col": "single diatom", "ex": "Diatom is a single-cell algae.", "pos": "n."},
  "diatonic": {"def": "(樂)全音階的人的人物 (單數) (音)", "ipa": "/ˌdaɪəˈtɒnɪk/", "trans": "scale", "col": "diatonic scale", "ex": "He played a diatonic scale.", "pos": "adj./n."},
  "diatribe": {"def": "謾罵、諷刺、抨擊、磨難人物 (單數) (罵)", "ipa": "/ˈdaɪətraɪb/", "trans": "attack", "col": "bitter diatribe", "ex": "He gave a bitter diatribe.", "pos": "n."},
  "dibble": {"def": "點播機、穴播的人物、穴播的人的人人物 (單數) (播)", "ipa": "/ˈdɪbl/", "trans": "tool", "col": "wooden dibble", "ex": "Use the_dibble for seeds.", "pos": "n./v./adj."},
  "dice": {"def": "骰子、色子的人物、切丁的人的人人物 (單數) (骰/丁)", "ipa": "/daɪs/", "trans": "diced", "col": "roll the_dice, no dice (不行), dice with death", "ex": "Roll the_dice and see the_luck.", "pos": "n./v./adj./adv."},
  "diced": {"def": "切成丁的、方旗狀的人的人 (或物) (丁)", "ipa": "/daɪst/", "trans": "dice", "col": "diced carrot, diced meat", "ex": "Add the_diced meat now.", "pos": "adj./v."},
  "dicephalous": {"def": "雙頭的人的人物 (單數) (雙)", "ipa": "/daɪˈsefələs/", "trans": "head", "col": "dicephalous twin", "ex": "It was a dicephalous specimen.", "pos": "adj./n."},
  "dicey": {"def": "危險的、冒險地 (危)", "ipa": "/ˈdaɪsi/", "trans": "risky", "col": "bit dicey", "ex": "The_situation looks a bit dicey.", "pos": "adj./adv."},
  "dichloride": {"def": "(化)二氯化物人物 (單數) (化)", "ipa": "/daɪˈklɔːraɪd/", "trans": "chemical", "col": "calcium dichloride", "ex": "It was a calcium dichloride mix.", "pos": "n."},
  "dichotomize/dichotomise": {"def": "分成兩半、對立的人的人", "ipa": "/daɪˈkɒtəmaɪz/", "trans": "split", "col": "dichotomize group", "ex": "Try to dichotomize the_issue.", "pos": "v./n./adv."},
  "dichotomic/dichotomous": {"def": "兩分的、對立的人的人物 (單數) (分)", "ipa": "/daɪˈkɒtəməs/", "trans": "dichotomy", "col": "dichotomous key", "ex": "It has a dichotomous choice.", "pos": "adj./n."},
  "dichotomy": {"def": "兩分、對立、二分法人物 (單數) (分)", "ipa": "/daɪˈkɒtəmi/", "trans": "dichotomous", "col": "false dichotomy, sharp dichotomy", "ex": "It's a false dichotomy here.", "pos": "n."},
  "dichroism": {"def": "二色性人物 (單數) (色)", "ipa": "/ˈdaɪkrəʊɪzm/", "trans": "color", "col": "optical dichroism", "ex": "The_gem showed dichroism.", "pos": "n."},
  "dick": {"def": "(俚)偵探、傢伙、(俗)陰莖的人物 (單數) (傢)", "ipa": "/dɪk/", "trans": "guy", "col": "clever dick", "ex": "He is a real clever dick now.", "pos": "n./adj."},
  "dickey/dicky": {"def": "(襯衫)假領、小鳥、健康不佳的人物 (單數) (領)", "ipa": "/ˈdɪki/", "trans": "bird", "col": "dicky heart (弱心臟), dicky bird", "ex": "He has a dicky heart tonight.", "pos": "n./adj."},
  "dickhead": {"def": "(俚)笨蛋、混蛋人物 (單數) (笨)", "ipa": "/ˈdɪkhed/", "trans": "fool", "col": "don't be a dickhead", "ex": "Don't be a total dickhead.", "pos": "n."},
  "dicotyledon": {"def": "(植)雙子葉植物人物 (單數) (植)", "ipa": "/ˌdaɪˌkɒtɪˈliːdn/", "trans": "plant", "col": "typical dicotyledon", "ex": "The_bean is a dicotyledon.", "pos": "n."},
  "dict-": {"def": "說、命令的人的人人物 (單數) (說)", "ipa": "/dɪkt-/", "trans": "speak", "col": "dictate", "ex": "He tried to dictate rules.", "pos": "pref./n./adj."},
  "dictate": {"def": "口述、命令、規定的人的人人物 (單數) (命)", "ipa": "/dɪkˈteɪt/", "trans": "dictation", "col": "dictate letter, dictate terms", "ex": "He began to dictate a letter.", "pos": "v./n./adj./adv."},
  "dictation": {"def": "聽寫、口述、命令人物 (單數) (聽)", "ipa": "/dɪkˈteɪʃn/", "trans": "dictate", "col": "take dictation, teacher's dictation", "ex": "She took the_manager's dictation.", "pos": "n."},
  "dictator": {"def": "獨裁者、發令者人物 (單數) (獨)", "ipa": "/dɪkˈteɪtə/", "trans": "dictatorship", "col": "absolute dictator, military dictator", "ex": "He was an absolute dictator.", "pos": "n."},
}
