{
  "deserving": {"def": "值得的、應得的人 (或物) (值)", "ipa": "/dɪˈzɜːvɪŋ/", "trans": "deserve", "col": "deserving cause, deserving cases", "ex": "He is a very deserving student.", "pos": "adj./n./adv."},
  "desiccate": {"def": "使脫水、使乾、使枯燥的人的人", "ipa": "/ˈdesɪkeɪt/", "trans": "dry", "col": "desiccate coconut", "ex": "Heat can desiccate the_soil.", "pos": "v./n./adv."},
  "desiccation": {"def": "乾燥、脫水人物 (單數) (乾)", "ipa": "/ˌdesɪˈkeɪʃn/", "trans": "desiccate", "col": "total desiccation", "ex": "Desiccation killed the_plants.", "pos": "n."},
  "desiccative": {"def": "使乾燥的人的人物 (單數) (劑)", "ipa": "/ˈdesɪkətɪv/", "trans": "desiccate", "col": "use a desiccative", "ex": "A desiccative agent was used.", "pos": "adj./n."},
  "desiderate": {"def": "渴望、願望的人的人", "ipa": "/dɪˈzɪdəreɪt/", "trans": "desire", "col": "desiderate peace", "ex": "They desiderate a quick end.", "pos": "v./n./adv."},
  "desiderative": {"def": "(語)欲求的、表示願望的人的人物 (單數) (欲)", "ipa": "/dɪˈzɪdərətɪv/", "trans": "desire", "col": "desiderative verb", "ex": "The_mood is desiderative here.", "pos": "adj./n."},
  "desideratum": {"def": "渴望之物、需要的東西人物 (單數) (欲)", "ipa": "/dɪˌzɪdəˈreɪtəm/", "trans": "goal", "col": "the_great desideratum", "ex": "Peace is the_great desideratum.", "pos": "n."},
  "design": {"def": "設計、圖樣、企圖的人的人人物 (單數) (設)", "ipa": "/dɪˈzaɪn/", "trans": "designer", "col": "by design, have designs on, interior design", "ex": "I met him by local design, not luck.", "pos": "v./n./adj./adv."},
  "designate": {"def": "指派、命名、標出、指定的的人的人人物 (單數) (指)", "ipa": "/ˈdezɪɡneɪt/", "trans": "designation", "col": "designate as, bishop designate", "ex": "He was designate as the_leader.", "pos": "v./n./adj./adv."},
  "designation": {"def": "指定、名稱、職銜人物 (單數) (銜)", "ipa": "/ˌdezɪɡˈneɪʃn/", "trans": "designate", "col": "official designation", "ex": "The_official designation is key.", "pos": "n."},
  "designated": {"def": "指定的、指派的人的人 (或物) (指)", "ipa": "/ˈdezɪɡneɪtɪd/", "trans": "designate", "col": "designated driver, designated area", "ex": "He was the_designated driver.", "pos": "adj./v."},
  "designer": {"def": "設計者、謀劃者、名師設計的人的人物 (單數) (設)", "ipa": "/dɪˈzaɪnə/", "trans": "design", "col": "fashion designer, designer drug", "ex": "The_fashion designer won a prize.", "pos": "n./adj."},
  "designing": {"def": "陰險的、有詭計的、設計的人 (或物) (險)", "ipa": "/dɪˈzaɪnɪŋ/", "trans": "design", "col": "designing woman", "ex": "He is a very designing man.", "pos": "adj./n./adv."},
  "desirability": {"def": "願望、有利、吸引力人物 (單數) (欲)", "ipa": "/dɪˌzaɪərəˈbɪləti/", "trans": "desirable", "col": "social desirability", "ex": "The_desirability of the_plan.", "pos": "n."},
  "desirable": {"def": "值得擁有的、合意地 (欲)", "ipa": "/dɪˈzaɪərəbl/", "trans": "desire", "col": "highly desirable", "ex": "It's a very highly desirable job.", "pos": "adj./adv."},
  "desire": {"def": "欲望、渴望、請求的人的人人物 (單數) (欲)", "ipa": "/dɪˈzaɪə/", "trans": "desirous", "col": "desire for, leave much to be desired (差強人意)", "ex": "His work leave much to be desired.", "pos": "v./n./adj./adv."},
  "desirous": {"def": "渴望的、想得到的的人的人物 (單數) (欲)", "ipa": "/dɪˈzaɪərəs/", "trans": "desire", "col": "desirous of", "ex": "She is desirous of a new life.", "pos": "adj./n."},
  "desist": {"def": "停止、結束的人的人", "ipa": "/dɪˈsɪst/", "trans": "stop", "col": "desist from", "ex": "Order them to desist from it.", "pos": "v./n./adv."},
  "desk": {"def": "辦公桌、服務台人物 (單數) (桌)", "ipa": "/desk/", "trans": "table", "col": "information desk, check-in desk, city desk", "ex": "He works at the_city desk.", "pos": "n."},
  "desmid": {"def": "(植)鼓藻人物 (單數) (藻)", "ipa": "/ˈdesmɪd/", "trans": "algae", "col": "green desmid", "ex": "Desmid is a type of green algae.", "pos": "n."},
  "desmine": {"def": "(礦)束沸石人物 (單數) (礦)", "ipa": "/ˈdesmiːn/", "trans": "stone", "col": "crystal desmine", "ex": "He found a piece of crystal desmine.", "pos": "n."},
  "desolate": {"def": "荒涼的、被遺棄的、使荒蕪的人的人人物 (單數) (荒)", "ipa": "/ˈdesələt/", "trans": "desolation", "col": "desolate place, feel desolate", "ex": "The_town looked desolate after war.", "pos": "adj./v./adv."},
}
